hyperc/__init__.py
hyperc/actions.py
hyperc/arithmetic.py
hyperc/auto_side_effect.py
hyperc/equal_object.py
hyperc/evolutionary.py
hyperc/examples/__init__.py
hyperc/examples/argsets.py
hyperc/examples/assert_basic.py
hyperc/examples/mcdc.py
hyperc/examples/simple.py
hyperc/examples/simple_hcproxy.py
hyperc/examples/simple_inheritance.py
hyperc/examples/simple_mcdc.py
hyperc/examples/simple_methods.py
hyperc/examples/simple_sets.py
hyperc/examples/web_app.py
hyperc/exceptions.py
hyperc/hc.py
hyperc/knifeGroundLimit.py
hyperc/main.py
hyperc/mcdc.py
hyperc/pddl.py
hyperc/pddlSplitter.py
hyperc/poc_symex.py
hyperc/proxies.py
hyperc/rtx.xtj
hyperc/running.py
hyperc/sas_collector.py
hyperc/sas_shuffle.py
hyperc/se_decoder.py
hyperc/settings.py
hyperc/solver.py
hyperc/text_pddlSplitter.py
hyperc/util.py
hyperc/web_ff_inter.py
hyperc/world.py
hyperc/xtj.py
hyperc-0.0.1.dist-info/entry_points.txt
hyperc-0.0.1.dist-info/WHEEL
hyperc-0.0.1.dist-info/METADATA
hyperc-0.0.1.dist-info/RECORD
