Metadata-Version: 2.1
Name: hyperc
Version: 0.0.1
Summary: Python AI Planning and automated programming
Home-page: https://github.com/hyperc-ai/hyperc
License: Proprietary
Keywords: ai,ai-planning,constraint-programming,automated-planning,optimization,compilers
Author: Andrew Gree
Author-email: andrew@hyperc.com
Requires-Python: >=3.7
Classifier: Development Status :: 3 - Alpha
Classifier: Intended Audience :: Developers
Classifier: License :: Other/Proprietary License
Classifier: Operating System :: POSIX :: Linux
Classifier: Programming Language :: Python :: 3
Classifier: Programming Language :: Python :: 3.7
Classifier: Programming Language :: Python :: 3.8
Classifier: Programming Language :: Python :: 3.9
Classifier: Topic :: Scientific/Engineering :: Artificial Intelligence
Classifier: Topic :: Software Development :: Libraries :: Python Modules
Requires-Dist: dill (>=0.3.2)
Requires-Dist: diskcache (>=4.1.0,<5.0.0)
Requires-Dist: downward_ch (>=0.0.9)
Requires-Dist: formulas (>=1.0.0,<2.0.0)
Requires-Dist: psutil (>=5.7)
Requires-Dist: unidecode (>=1.1.1)
Requires-Dist: wrapt (==1.11.2)
Project-URL: Repository, https://github.com/hyperc-ai/hyperc
